comets/__init__.py
comets/core/__init__.py
comets/core/experiment.py
comets/core/modelinterface.py
comets/core/modeltask.py
comets/core/parallelmanager.py
comets/core/parameterset.py
comets/core/space.py
comets/core/stopcriteria.py
comets/core/task.py
comets/experiments/__init__.py
comets/experiments/optimization/__init__.py
comets/experiments/optimization/bayesianoptimizer.py
comets/experiments/optimization/cmaes.py
comets/experiments/optimization/configgeneticalgorithm.py
comets/experiments/optimization/constrainthandler.py
comets/experiments/optimization/evolutionstrategies.py
comets/experiments/optimization/nevergradalgorithm.py
comets/experiments/optimization/optimalgorithm.py
comets/experiments/optimization/optimization.py
comets/experiments/optimization/pymooalgorithm.py
comets/experiments/optimization/space_optim.py
comets/experiments/parameterscan/__init__.py
comets/experiments/parameterscan/parameterscan.py
comets/experiments/parametersweep/__init__.py
comets/experiments/parametersweep/parametersweep.py
comets/experiments/parametersweep/space_parametersweep.py
comets/experiments/reinforcementlearning/__init__.py
comets/experiments/reinforcementlearning/reinforcementlearningenv.py
comets/experiments/sensitivity/OAT.py
comets/experiments/sensitivity/SALib.py
comets/experiments/sensitivity/__init__.py
comets/experiments/sensitivity/globalsensitivityanalysis.py
comets/experiments/sensitivity/localsensitivityanalysis.py
comets/experiments/sensitivity/sensitivityanalyzer.py
comets/experiments/surrogate/__init__.py
comets/experiments/surrogate/scikitlearnsurrogate.py
comets/experiments/surrogate/surrogate.py
comets/experiments/surrogate/surrogatemodeling.py
comets/experiments/uncertainty/__init__.py
comets/experiments/uncertainty/analyzer.py
comets/experiments/uncertainty/descriptivestats.py
comets/experiments/uncertainty/stat_stopping_criteria.py
comets/experiments/uncertainty/uncertaintyanalysis.py
comets/modelinterfaces/__init__.py
comets-1.5.2.dist-info/licenses/LICENSE
comets-1.5.2.dist-info/METADATA
comets-1.5.2.dist-info/WHEEL
comets-1.5.2.dist-info/top_level.txt
comets-1.5.2.dist-info/RECORD
